texercise/__init__.py
texercise/version.py
texercise/echo_exercise/solution/CMakeLists.txt
texercise/echo_exercise/solution/echo.cpp
texercise/echo_exercise/template/CMakeLists.txt
texercise/echo_exercise/template/echo.cpp
texercise/echo_exercise/tests/test_a.txt
texercise/echo_exercise/tests/test_b.txt
texercise-0.0.12.data/scripts/texercise
texercise-0.0.12.dist-info/METADATA
texercise-0.0.12.dist-info/WHEEL
texercise-0.0.12.dist-info/top_level.txt
texercise-0.0.12.dist-info/RECORD
