Metadata-Version: 2.1
Name: texercise
Version: 0.0.12
Summary: command line interface for exercises
Home-page: https://github.com/RasmusHaugaard/texercise-cli
Author: Rasmus Laurvig Haugaard
Author-email: rasmus.l.haugaard@gmail.com
License: UNKNOWN
Platform: UNKNOWN
Requires-Python: >=3.6
Requires-Dist: request
Requires-Dist: click
Requires-Dist: tabulate
